setup.py
msg_srv.egg-info/PKG-INFO
msg_srv.egg-info/SOURCES.txt
msg_srv.egg-info/dependency_links.txt
msg_srv.egg-info/requires.txt
msg_srv.egg-info/top_level.txt
server/__init__.py
server/srvr.py
server/common/__init__.py
server/common/decos.py
server/common/descriptors.py
server/common/errors.py
server/common/metaclasses.py
server/common/utils.py
server/common/variables.py
server/logs/__init__.py
server/logs/config_log_client.py
server/logs/config_log_other.py
server/logs/config_log_server.py
server/server/__init__.py
server/server/core — копия.py
server/server/core.py
server/server/srv_db.py
server/server/srv_gui.py
server/server/win_add_user.py
server/server/win_config.py
server/server/win_hist.py
server/server/win_rem_user.py
server/unit_tests/__init__.py
server/unit_tests/test_client.py
server/unit_tests/test_server.py