Metadata-Version: 2.1
Name: msg-srv
Version: 0.0.1
Summary: messages_server
Home-page: UNKNOWN
Author: KolesnikIvan
License: UNKNOWN
Platform: UNKNOWN
